{
  "tags": [
    {
      "name": "release",
      "version": "10.7.6-1",
      "commit": "0303dcf",
      "upstream": "Stable",
      "lastUpdated": "2021-08-12T14:00:45.665Z"
    },
    {
      "name": "testing",
      "version": "10.7.0-rc4",
      "commit": "ee8bb80",
      "upstream": "RC",
      "lastUpdated": "2021-08-12T14:00:18.551Z"
    },
    {
      "name": "nightly",
      "version": "20210813.3",
      "commit": "7bf0a1b",
      "upstream": "Unstable",
      "lastUpdated": "2021-08-13T16:55:41.726Z"
    }
  ],
  "pulls": 797097,
  "stars": 5
}
