{
  "tags": [
    {
      "name": "release",
      "version": "10.7.7-1",
      "commit": "95879fc",
      "upstream": "Stable",
      "lastUpdated": "2022-03-18T07:23:44.407Z"
    },
    {
      "name": "testing",
      "version": "",
      "commit": "",
      "upstream": "",
      "lastUpdated": ""
    },
    {
      "name": "nightly",
      "version": "20220404.16",
      "commit": "b45b488",
      "upstream": "Unstable",
      "lastUpdated": "2022-04-04T15:13:02.836Z"
    }
  ],
  "pulls": 1248986,
  "stars": 9
}
