{
  "tags": [
    {
      "name": "release",
      "version": "10.7.7-1",
      "commit": "95879fc",
      "upstream": "Stable",
      "lastUpdated": "2022-03-18T07:23:44.407Z"
    },
    {
      "name": "testing",
      "version": "",
      "commit": "",
      "upstream": "",
      "lastUpdated": ""
    },
    {
      "name": "nightly",
      "version": "20220317.2",
      "commit": "9503e54",
      "upstream": "Unstable",
      "lastUpdated": "2022-03-18T07:23:27.677Z"
    }
  ],
  "pulls": 1246487,
  "stars": 9
}
